xbin_render.py
xbin_render-0.1.0.dist-info/METADATA
xbin_render-0.1.0.dist-info/WHEEL
xbin_render-0.1.0.dist-info/entry_points.txt
xbin_render-0.1.0.dist-info/licenses/COPYING.WTFPL
xbin_render-0.1.0.dist-info/RECORD
