Metadata-Version: 2.3
Name: xbin_render
Version: 0.1.0
Summary: Convert XBin images to PNG or to terminal
Project-URL: Homepage, https://gitlab.com/hydrargyrum/xbin_render
License-Expression: WTFPL
License-File: COPYING.WTFPL
Keywords: ansi,ascii,image,terminal,xbin
Classifier: Development Status :: 4 - Beta
Classifier: Intended Audience :: Developers
Classifier: License :: Public Domain
Classifier: Programming Language :: Python :: 3
Classifier: Programming Language :: Python :: 3.7
Classifier: Programming Language :: Python :: 3.8
Classifier: Programming Language :: Python :: 3.9
Classifier: Programming Language :: Python :: 3.10
Classifier: Programming Language :: Python :: 3.11
Classifier: Programming Language :: Python :: 3.12
Classifier: Topic :: Desktop Environment
Classifier: Topic :: Multimedia :: Graphics
Classifier: Topic :: Software Development :: Libraries :: Python Modules
Classifier: Topic :: Utilities
Requires-Python: >=3
Requires-Dist: pillow
